client/__init__.py
client/mongodb/__init__.py
client/mongodb/mongo_client.py
client/queue/__init__.py
client/queue/queue.py
client/queue/mongodb/__init__.py
client/queue/mongodb/mongo_queue.py
client/queue/structure/__init__.py
client/queue/structure/message.py
client/queue/structure/queue_monitor.py
client/structures/__init__.py
client/structures/tasks/__init__.py
client/structures/tasks/find_trend_task.py
client/structures/tasks/pe_task.py
client/user_manager/__init__.py
client/user_manager/structure/__init__.py
client/user_manager/structure/user.py
test/__init__.py
PZClient-0.0.2.dist-info/LICENSE
PZClient-0.0.2.dist-info/METADATA
PZClient-0.0.2.dist-info/WHEEL
PZClient-0.0.2.dist-info/top_level.txt
PZClient-0.0.2.dist-info/RECORD
