Metadata-Version: 2.1
Name: PZClient
Version: 0.0.2
Summary: A client for who wants to integrate with PZStocks
Home-page: https://gitlab.com/Ram_and_Zada_stocks/PZClient/
Author: PZStocks
Author-email: ramperel98@gmail.com
License: UNKNOWN
Platform: UNKNOWN
Classifier: Programming Language :: Python :: 3
Classifier: License :: OSI Approved :: MIT License
Classifier: Operating System :: OS Independent
Requires-Python: >=3.6
